MANIFEST.in
README.rst
setup.py
gender_ai/__init__.py
gender_ai.egg-info/PKG-INFO
gender_ai.egg-info/SOURCES.txt
gender_ai.egg-info/dependency_links.txt
gender_ai.egg-info/not-zip-safe
gender_ai.egg-info/requires.txt
gender_ai.egg-info/top_level.txt