Metadata-Version: 1.1
Name: gender-ai
Version: 0.1
Summary: Neural Network to predict Gender from first name
Home-page: http://github.com/leophagus/gender_ai
Author: leophagus
Author-email: UNKNOWN
License: MIT
Platform: UNKNOWN
Classifier: Development Status :: 3 - Alpha
Classifier: License :: OSI Approved :: MIT License
Classifier: Programming Language :: Python :: 2.7
Classifier: Topic :: Scientific/Engineering :: Artificial Intelligence
Classifier: Topic :: Text Processing :: Linguistic
